transcribe_anything/WHISPER_OPTIONS.json
transcribe_anything/__init__.py
transcribe_anything/__main__.py
transcribe_anything/_cmd.py
transcribe_anything/api.py
transcribe_anything/audio.py
transcribe_anything/cli_init_insane.py
transcribe_anything/cuda_available.py
transcribe_anything/generate_speaker_json.py
transcribe_anything/insanely_fast_whisper.py
transcribe_anything/insanley_fast_whisper_reqs.py
transcribe_anything/install_whisper.py
transcribe_anything/logger.py
transcribe_anything/parse_whisper_options.py
transcribe_anything/srt_translation.py
transcribe_anything/srt_wrap.py
transcribe_anything/util.py
transcribe_anything/whisper.py
transcribe_anything/whisper_mac.py
transcribe_anything/ytldp_download.py
transcribe_anything/archive/install_cuda.py
transcribe_anything/assets/sample.mp3
transcribe_anything-3.2.4.dist-info/licenses/LICENSE
transcribe_anything-3.2.4.dist-info/METADATA
transcribe_anything-3.2.4.dist-info/WHEEL
transcribe_anything-3.2.4.dist-info/entry_points.txt
transcribe_anything-3.2.4.dist-info/top_level.txt
transcribe_anything-3.2.4.dist-info/RECORD
