Metadata-Version: 2.4
Name: transcribe-anything
Version: 3.2.4
Summary: Uses Whisper AI to transcribe speech from video and audio files. Also accepts URLs for YouTube, Rumble, BitChute, clear file links, etc.
Maintainer-email: Zachary Vorhies <dont@email.me>
License: BSD-3-Clause
Project-URL: homepage, https://github.com/zackees/transcribe-anything
Keywords: transcribe,openai,whisper
Requires-Python: >=3.10
License-File: LICENSE
Requires-Dist: static-ffmpeg>=2.7
Requires-Dist: yt-dlp>=2025.1.15
Requires-Dist: appdirs>=1.4.4
Requires-Dist: disklru>=1.0.7
Requires-Dist: FileLock
Requires-Dist: webvtt-py==0.4.6
Requires-Dist: uv-iso-env>=1.0.43
Requires-Dist: python-dotenv>=1.0.1
Dynamic: license-file
